{"Nodes":[],"ExecutionTime":"2024-06-09T17:40:04.7652691Z","GenerationTime":"0001-01-01T00:00:00","PluginUserSpecFlowId":"cb857755-3e04-4ce6-a89f-a015febf0c40","CLIUserSpecFlowId":null,"ExecutionResults":[{"ContextType":"Scenario","FeatureFolderPath":"Features","FeatureTitle":"addToCart","ScenarioTitle":"as a user I can add items to the cart","ScenarioArguments":["sauce-labs-backpack"],"Status":"OK","StepResults":[{"Duration":"00:00:03.9482075","Status":"OK","Error":null,"Outputs":null},{"Duration":"00:00:00.0120296","Status":"OK","Error":null,"Outputs":null},{"Duration":"00:00:00.0503427","Status":"OK","Error":null,"Outputs":null},{"Duration":"00:00:00.0339461","Status":"OK","Error":null,"Outputs":null}],"Outputs":null},{"ContextType":"Scenario","FeatureFolderPath":"Features","FeatureTitle":"addToCart","ScenarioTitle":"as a user I can add items to the cart","ScenarioArguments":["sauce-labs-bike-light"],"Status":"OK","StepResults":[{"Duration":"00:00:00.2948506","Status":"OK","Error":null,"Outputs":null},{"Duration":"00:00:00.0154348","Status":"OK","Error":null,"Outputs":null},{"Duration":"00:00:00.0483827","Status":"OK","Error":null,"Outputs":null},{"Duration":"00:00:00.0213613","Status":"OK","Error":null,"Outputs":null}],"Outputs":null},{"ContextType":"Scenario","FeatureFolderPath":"Features","FeatureTitle":"addToCart","ScenarioTitle":"as a user I can add items to the cart","ScenarioArguments":["sauce-labs-bolt-t-shirt"],"Status":"OK","StepResults":[{"Duration":"00:00:00.3415825","Status":"OK","Error":null,"Outputs":null},{"Duration":"00:00:00.0057206","Status":"OK","Error":null,"Outputs":null},{"Duration":"00:00:00.0483671","Status":"OK","Error":null,"Outputs":null},{"Duration":"00:00:00.0164219","Status":"OK","Error":null,"Outputs":null}],"Outputs":null},{"ContextType":"Scenario","FeatureFolderPath":"Features","FeatureTitle":"addToCart","ScenarioTitle":"as a user I can add items to the cart","ScenarioArguments":["sauce-labs-fleece-jacket"],"Status":"OK","StepResults":[{"Duration":"00:00:00.2641884","Status":"OK","Error":null,"Outputs":null},{"Duration":"00:00:00.0063394","Status":"OK","Error":null,"Outputs":null},{"Duration":"00:00:00.0593330","Status":"OK","Error":null,"Outputs":null},{"Duration":"00:00:00.0215111","Status":"OK","Error":null,"Outputs":null}],"Outputs":null},{"ContextType":"Scenario","FeatureFolderPath":"Features","FeatureTitle":"addToCart","ScenarioTitle":"as a user I can add items to the cart","ScenarioArguments":["test.allthethings()-t-shirt-(red)"],"Status":"OK","StepResults":[{"Duration":"00:00:00.2730997","Status":"OK","Error":null,"Outputs":null},{"Duration":"00:00:00.0092688","Status":"OK","Error":null,"Outputs":null},{"Duration":"00:00:00.0437834","Status":"OK","Error":null,"Outputs":null},{"Duration":"00:00:00.0162386","Status":"OK","Error":null,"Outputs":null}],"Outputs":null},{"ContextType":"Scenario","FeatureFolderPath":"Features","FeatureTitle":"addToCart","ScenarioTitle":"as a user I can add items to the cart","ScenarioArguments":["sauce-labs-onesie"],"Status":"OK","StepResults":[{"Duration":"00:00:00.2549057","Status":"OK","Error":null,"Outputs":null},{"Duration":"00:00:00.0045137","Status":"OK","Error":null,"Outputs":null},{"Duration":"00:00:00.0470510","Status":"OK","Error":null,"Outputs":null},{"Duration":"00:00:00.0159003","Status":"OK","Error":null,"Outputs":null}],"Outputs":null},{"ContextType":"Scenario","FeatureFolderPath":"Features","FeatureTitle":"checkout","ScenarioTitle":"User can checkout","ScenarioArguments":[],"Status":"OK","StepResults":[{"Duration":"00:00:00.2523271","Status":"OK","Error":null,"Outputs":null},{"Duration":"00:00:00.1107846","Status":"OK","Error":null,"Outputs":null},{"Duration":"00:00:00.1972058","Status":"OK","Error":null,"Outputs":null},{"Duration":"00:00:00.1323116","Status":"OK","Error":null,"Outputs":null},{"Duration":"00:00:00.0228074","Status":"OK","Error":null,"Outputs":null}],"Outputs":null},{"ContextType":"Scenario","FeatureFolderPath":"Features","FeatureTitle":"login","ScenarioTitle":"Invalid user cannot log in","ScenarioArguments":["Username and password do not match any user in this service"],"Status":"OK","StepResults":[{"Duration":"00:00:00.0444255","Status":"OK","Error":null,"Outputs":null},{"Duration":"00:00:00.1531064","Status":"OK","Error":null,"Outputs":null},{"Duration":"00:00:00.0603292","Status":"OK","Error":null,"Outputs":null},{"Duration":"00:00:00.0226303","Status":"OK","Error":null,"Outputs":null}],"Outputs":null},{"ContextType":"Scenario","FeatureFolderPath":"Features","FeatureTitle":"login","ScenarioTitle":"Valid user can log in","ScenarioArguments":[],"Status":"OK","StepResults":[{"Duration":"00:00:00.0419603","Status":"OK","Error":null,"Outputs":null},{"Duration":"00:00:00.1378808","Status":"OK","Error":null,"Outputs":null},{"Duration":"00:00:00.0520909","Status":"OK","Error":null,"Outputs":null},{"Duration":"00:00:00.0052697","Status":"OK","Error":null,"Outputs":null}],"Outputs":null},{"ContextType":"Scenario","FeatureFolderPath":"Features","FeatureTitle":"logOut","ScenarioTitle":"I can log out from the website","ScenarioArguments":[],"Status":"OK","StepResults":[{"Duration":"00:00:00.2560117","Status":"OK","Error":null,"Outputs":null},{"Duration":"00:00:00.0072497","Status":"OK","Error":null,"Outputs":null},{"Duration":"00:00:00.6416979","Status":"OK","Error":null,"Outputs":null},{"Duration":"00:00:00.0045257","Status":"OK","Error":null,"Outputs":null}],"Outputs":null},{"ContextType":"Scenario","FeatureFolderPath":"Features","FeatureTitle":"ProductList","ScenarioTitle":"After I log in, the product list is displayed correctly","ScenarioArguments":[],"Status":"OK","StepResults":[{"Duration":"00:00:00.2499258","Status":"OK","Error":null,"Outputs":null},{"Duration":"00:00:00.0062672","Status":"OK","Error":null,"Outputs":null},{"Duration":"00:00:00.1069303","Status":"OK","Error":null,"Outputs":null}],"Outputs":null}],"StepReports":null}